[
{
	"id": 1,
	"name": "Elastic Force",
	"use": "[LMB]"
},
{
	"id": 2,
	"name": "Evasion",
	"use": "[SHIFT] + [A] OR [D]"
},
{
	"id": 3,
	"name": "Shake Off",
	"use": "[RMB] + [A] OR [D]"
},
{
	"id": 4,
	"name": "Seizing Fear",
	"use": "Passive"
},
{
	"id": 5,
	"name": "Smack Down",
	"use": "[E]"
},
{
	"id": 6,
	"name": "Corpse Storm",
	"use": "[LMB]"
},
{
	"id": 7,
	"name": "Undertaker",
	"use": "[SPACE]"
},
{
	"id": 8,
	"name": "Rock Smash",
	"use": "Skill Bar"
},
{
	"id": 9,
	"name": "Storming Beast",
	"use": "[F]"
},
{
	"id": 10,
	"name": "Headbutt",
	"use": "[RMB] + [W]"
},
{
	"id": 11,
	"name": "Tackling Rock",
	"use": "[W] + [F]"
},
{
	"id": 12,
	"name": "Predatory Hunt",
	"use": "[S] + [F]"
},
{
	"id": 13,
	"name": "Frenzied Destroyer",
	"use": "[LMB] + [S]"
},
{
	"id": 14,
	"name": "Fearsome Tyrant",
	"use": "[SHIFT] + [Q]"
},
{
	"id": 15,
	"name": "Raging Thunder",
	"use": "[LMB] + [RMB]"
}
]